enebular_sdk/__init__.py
enebular_sdk/common/__init__.py
enebular_sdk/common/logger.py
enebular_sdk/datastore/__init__.py
enebular_sdk/datastore/exceptions.py
enebular_sdk/datastore/constants/__init__.py
enebular_sdk/datastore/constants/env.py
enebular_sdk/datastore/constants/request.py
enebular_sdk/datastore/lambda_/__init__.py
enebular_sdk/datastore/lambda_/cloud_data_store_client.py
enebular_sdk/datastore/lambda_/proxy_client.py
enebular_sdk/datastore/types/__init__.py
enebular_sdk-1.0.0.dist-info/METADATA
enebular_sdk-1.0.0.dist-info/WHEEL
enebular_sdk-1.0.0.dist-info/top_level.txt
enebular_sdk-1.0.0.dist-info/RECORD
