Metadata-Version: 2.4
Name: enebular-sdk
Version: 1.0.0
Summary: enebularのクラウド実行環境上で動作するアプリケーションを開発するためのSDKです。
Author-email: Uhuru <enebular-operation@uhuru.jp>
License: MIT
Project-URL: Homepage, https://enebular.com
Project-URL: Documentation, https://docs.enebular.com/ja
Requires-Python: >=3.9
Requires-Dist: boto3>=1.26.0
